README.rst
setup.cfg
setup.py
cypress_common/__init__.py
cypress_common/common_helper.py
cypress_common/cypress_base.py
cypress_common/cypress_cache.py
cypress_common/cypress_exceptions.py
cypress_common/heart_beat_sender.py
cypress_common/kafka_helper.py
cypress_common/logger_helper.py
cypress_common/version.py
cypress_common.egg-info/PKG-INFO
cypress_common.egg-info/SOURCES.txt
cypress_common.egg-info/dependency_links.txt
cypress_common.egg-info/requires.txt
cypress_common.egg-info/top_level.txt
tests/resources/__init__.py
tests/resources/new_vector.py
tests/resources/old_vector.py