Metadata-Version: 1.0
Name: cypress-common
Version: 0.5.20
Summary: Istuary DeepVision Cypress Common Library
Home-page: https://www.istuary.com
Author: Istuary DeepVision Team (Cypress)
Author-email: cypress-dev@istuary.com
License: MIT
Platform: UNKNOWN
